ag_llama_api/__init__.py
ag_llama_api/__main__.py
ag_llama_api/choice.py
ag_llama_api/model.py
ag_llama_api/tokenizer.py
ag_llama_api-0.0.31.data/scripts/download.py
ag_llama_api-0.0.31.data/scripts/render.py
ag_llama_api-0.0.31.dist-info/METADATA
ag_llama_api-0.0.31.dist-info/WHEEL
ag_llama_api-0.0.31.dist-info/top_level.txt
ag_llama_api-0.0.31.dist-info/RECORD
